prodapp/__init__.py
prodapp/app.py
prodapp/app_state.py
prodapp/config.ini
prodapp/main.py
prodapp/sounds/bleep.mp3
prodapp/static/style.css
prodapp-0.8.2.dist-info/LICENSE
prodapp-0.8.2.dist-info/METADATA
prodapp-0.8.2.dist-info/WHEEL
prodapp-0.8.2.dist-info/top_level.txt
prodapp-0.8.2.dist-info/zip-safe
prodapp-0.8.2.dist-info/RECORD
