Metadata-Version: 2.1
Name: prodapp
Version: 0.8.2
Summary: Score yourself.
Home-page: https://github.com/OverLordGoldDragon/prodapp
Author: OverLordGoldDragon
Author-email: 16495490+OverLordGoldDragon@users.noreply.github.com
License: MIT
Keywords: productivity productivity-booster productivity-timer python-dash python
Platform: UNKNOWN
Classifier: Programming Language :: Python :: 3.6
Classifier: Programming Language :: Python :: 3.7
Classifier: Programming Language :: Python :: 3.8
Classifier: License :: OSI Approved :: MIT License
Classifier: Operating System :: OS Independent
Classifier: Intended Audience :: End Users/Desktop
Classifier: Intended Audience :: Information Technology
Classifier: Intended Audience :: Science/Research
Classifier: Topic :: Utilities
Classifier: Topic :: Software Development
Classifier: Topic :: Software Development :: Libraries :: Python Modules
Requires-Dist: dash
